EGDrive/__init__.py
EGDrive-0.1.3.dist-info/LICENSE.txt
EGDrive-0.1.3.dist-info/METADATA
EGDrive-0.1.3.dist-info/WHEEL
EGDrive-0.1.3.dist-info/top_level.txt
EGDrive-0.1.3.dist-info/RECORD
