Metadata-Version: 2.1
Name: EGDrive
Version: 0.1.3
Summary: A Simplified Google Drive API.
Home-page: https://github.com/th3c00lw0lf/EGDrive
Author: th3c00lw0lf
Author-email: business.mam@outlook.com
License: LICENSE.txt
Classifier: Programming Language :: Python :: 3
Classifier: Development Status :: 4 - Beta
Classifier: Operating System :: OS Independent
Classifier: Intended Audience :: Developers
Classifier: License :: OSI Approved :: Apache Software License
Classifier: Topic :: Communications :: File Sharing
Classifier: Topic :: Internet
Classifier: Topic :: Software Development :: Libraries
License-File: LICENSE.txt
Requires-Dist: cachetools (==5.2.0)
Requires-Dist: certifi (==2022.9.24)
Requires-Dist: cffi (==1.15.1)
Requires-Dist: charset-normalizer (==2.1.1)
Requires-Dist: commonmark (==0.9.1)
Requires-Dist: cryptography (==38.0.1)
Requires-Dist: google-api-core (==2.10.2)
Requires-Dist: google-api-python-client (==2.64.0)
Requires-Dist: google-auth (==2.12.0)
Requires-Dist: google-auth-httplib2 (==0.1.0)
Requires-Dist: googleapis-common-protos (==1.56.4)
Requires-Dist: httplib2 (==0.20.4)
Requires-Dist: idna (==3.4)
Requires-Dist: oauth2client (==4.1.3)
Requires-Dist: protobuf (==4.21.7)
Requires-Dist: pyasn1 (==0.4.8)
Requires-Dist: pyasn1-modules (==0.2.8)
Requires-Dist: pycparser (==2.21)
Requires-Dist: PyDrive2 (==1.14.0)
Requires-Dist: Pygments (==2.13.0)
Requires-Dist: pyOpenSSL (==22.1.0)
Requires-Dist: pyparsing (==3.0.9)
Requires-Dist: PyYAML (==6.0)
Requires-Dist: requests (==2.28.1)
Requires-Dist: rich (==12.6.0)
Requires-Dist: rsa (==4.9)
Requires-Dist: six (==1.16.0)
Requires-Dist: uritemplate (==4.1.1)
Requires-Dist: urllib3 (==1.26.12)
